odoo10_addon_dbfilter_from_header-10.0.1.0.0-py2.7-nspkg.pth
odoo10_addon_dbfilter_from_header-10.0.1.0.0.dist-info/top_level.txt
odoo10_addon_dbfilter_from_header-10.0.1.0.0.dist-info/WHEEL
odoo10_addon_dbfilter_from_header-10.0.1.0.0.dist-info/RECORD
odoo10_addon_dbfilter_from_header-10.0.1.0.0.dist-info/metadata.json
odoo10_addon_dbfilter_from_header-10.0.1.0.0.dist-info/DESCRIPTION.rst
odoo10_addon_dbfilter_from_header-10.0.1.0.0.dist-info/METADATA
odoo10_addon_dbfilter_from_header-10.0.1.0.0.dist-info/namespace_packages.txt
odoo/addons/dbfilter_from_header/__manifest__.py
odoo/addons/dbfilter_from_header/__init__.py
odoo/addons/dbfilter_from_header/README.rst
odoo/addons/dbfilter_from_header/i18n/dbfilter_from_header.pot
odoo/addons/dbfilter_from_header/static/description/icon.png
